odoo/addons/sale_coupon_most_expensive_delivery/README.rst
odoo/addons/sale_coupon_most_expensive_delivery/__init__.py
odoo/addons/sale_coupon_most_expensive_delivery/__manifest__.py
odoo/addons/sale_coupon_most_expensive_delivery/i18n/sale_coupon_most_expensive_delivery.pot
odoo/addons/sale_coupon_most_expensive_delivery/models/__init__.py
odoo/addons/sale_coupon_most_expensive_delivery/models/sale_order.py
odoo/addons/sale_coupon_most_expensive_delivery/readme/CONTRIBUTORS.rst
odoo/addons/sale_coupon_most_expensive_delivery/readme/DESCRIPTION.rst
odoo/addons/sale_coupon_most_expensive_delivery/static/description/icon.png
odoo/addons/sale_coupon_most_expensive_delivery/static/description/index.html
odoo/addons/sale_coupon_most_expensive_delivery/tests/__init__.py
odoo/addons/sale_coupon_most_expensive_delivery/tests/test_discount_apply_on.py
odoo13_addon_sale_coupon_most_expensive_delivery-13.0.1.0.1.dist-info/METADATA
odoo13_addon_sale_coupon_most_expensive_delivery-13.0.1.0.1.dist-info/WHEEL
odoo13_addon_sale_coupon_most_expensive_delivery-13.0.1.0.1.dist-info/top_level.txt
odoo13_addon_sale_coupon_most_expensive_delivery-13.0.1.0.1.dist-info/RECORD
